LICENSE
MANIFEST.in
README.md
pyproject.toml
setup.cfg
src/lib_pybroker.egg-info/PKG-INFO
src/lib_pybroker.egg-info/SOURCES.txt
src/lib_pybroker.egg-info/dependency_links.txt
src/lib_pybroker.egg-info/requires.txt
src/lib_pybroker.egg-info/top_level.txt
src/pybroker/__init__.py
src/pybroker/cache.py
src/pybroker/common.py
src/pybroker/config.py
src/pybroker/context.py
src/pybroker/data.py
src/pybroker/eval.py
src/pybroker/indicator.py
src/pybroker/log.py
src/pybroker/model.py
src/pybroker/portfolio.py
src/pybroker/py.typed
src/pybroker/scope.py
src/pybroker/slippage.py
src/pybroker/strategy.py
src/pybroker/vect.py
src/pybroker/ext/__init__.py
src/pybroker/ext/data.py
tests/test_cache.py
tests/test_common.py
tests/test_context.py
tests/test_data.py
tests/test_eval.py
tests/test_indicator.py
tests/test_log.py
tests/test_model.py
tests/test_portfolio.py
tests/test_scope.py
tests/test_slippage.py
tests/test_strategy.py
tests/test_vect.py