Metadata-Version: 2.4
Name: lib-pybroker
Version: 1.2.11
Summary: Algorithmic trading with machine learning
Home-page: http://www.pybroker.com
Author: Edward West
Author-email: edwest@pybroker.com
License: Apache License 2.0 with Commons Clause
Classifier: License :: Free for non-commercial use
License-File: LICENSE
Requires-Dist: akshare<2,>=1.10.1
Requires-Dist: alpaca-py<1,>=0.7.2
Requires-Dist: diskcache<6,>=5.4.0
Requires-Dist: joblib<2,>=1.2.0
Requires-Dist: numba<1,>=0.60.0
Requires-Dist: numpy<3,>=1.26.4
Requires-Dist: pandas<3,>=2.2.0
Requires-Dist: progressbar2<5,>=4.1.1
Requires-Dist: yahooquery<3,>=2.3.7
Requires-Dist: yfinance<1,>=0.2.55
Dynamic: license-file
